[{"url":"https://www.heavens-above.com/passdetails.aspx?lat=39.9042&lng=116.4074&loc=%e5%8c%97%e4%ba%ac%e5%b8%82&alt=52&tz=ChST&satid=25544&mjd=61128.4778362217&type=A","date":"3月29日","brightness":"-3.6","events":{"rise":{"time":"19:22:35","altitude":"0°","azimuth":"306° (西北)","distance":"2,378","brightness":"1.5","sunAltitude":"-9.8°"},"reachAltitude10deg":{"time":"19:24:41","altitude":"10°","azimuth":"305° (西北)","distance":"1,509","brightness":"0.3","sunAltitude":"-10.2°"},"highestPoint":{"time":"19:28:04","altitude":"76°","azimuth":"220° (西南)","distance":"438","brightness":"-3.6","sunAltitude":"-10.8°"},"enterShadow":{"time":"19:30:49","altitude":"15°","azimuth":"135° (东南)","distance":"1,253","brightness":"-1.9","sunAltitude":"-11.3°"},"dropBelowAltitude10deg":{"time":"19:31:26","altitude":"10°","azimuth":"134° (东南)","distance":"1,497","brightness":"-","sunAltitude":"-11.4°"},"set":{"time":"19:33:31","altitude":"0°","azimuth":"132° (东南)","distance":"2,356","brightness":"-","sunAltitude":"-11.8°"}},"passType":"可见","image":"https://www.heavens-above.com/PassSkyChart2.ashx?passID=362872&size=800&lat=39.9042&lng=116.4074&loc=%e5%8c%97%e4%ba%ac%e5%b8%82&alt=52&tz=ChST&showUnlit=true","scoreData":[19,-3.6,-10.8,76],"exist":368,"score":74,"id":"5722f376abce03c51a47945d5545345b"},{"url":"https://www.heavens-above.com/passdetails.aspx?lat=39.9042&lng=116.4074&loc=%e5%8c%97%e4%ba%ac%e5%b8%82&alt=52&tz=ChST&satid=25544&mjd=61125.5086991057&type=A","date":"3月26日","brightness":"-3.6","events":{"rise":{"time":"20:07:02","altitude":"0°","azimuth":"309° (西北)","distance":"2,379","brightness":"1.4","sunAltitude":"-18.6°"},"reachAltitude10deg":{"time":"20:09:10","altitude":"10°","azimuth":"313° (西北)","distance":"1,510","brightness":"0.1","sunAltitude":"-19.0°"},"highestPoint":{"time":"20:12:31","altitude":"61°","azimuth":"34° (东北)","distance":"483","brightness":"-3.6","sunAltitude":"-19.6°"},"enterShadow":{"time":"20:12:32","altitude":"61°","azimuth":"36° (东北)","distance":"483","brightness":"-3.6","sunAltitude":"-19.6°"},"dropBelowAltitude10deg":{"time":"20:15:51","altitude":"10°","azimuth":"116° (东南偏东)","distance":"1,499","brightness":"-","sunAltitude":"-20.2°"},"set":{"time":"20:17:58","altitude":"0°","azimuth":"120° (东南偏东)","distance":"2,358","brightness":"-","sunAltitude":"-20.6°"}},"passType":"可见","image":"https://www.heavens-above.com/PassSkyChart2.ashx?passID=362573&size=800&lat=39.9042&lng=116.4074&loc=%e5%8c%97%e4%ba%ac%e5%b8%82&alt=52&tz=ChST&showUnlit=true","scoreData":[20,-3.6,-19.6,61],"exist":202,"score":74,"id":"a44d0fcf8ab18d91f18fa8cf5678b1fa"},{"url":"https://www.heavens-above.com/passdetails.aspx?lat=39.9042&lng=116.4074&loc=%e5%8c%97%e4%ba%ac%e5%b8%82&alt=52&tz=ChST&satid=25544&mjd=61127.5105129873&type=A","date":"3月28日","brightness":"-2.9","events":{"rise":{"time":"20:09:44","altitude":"0°","azimuth":"302° (西北偏西)","distance":"2,377","brightness":"1.6","sunAltitude":"-18.6°"},"reachAltitude10deg":{"time":"20:11:55","altitude":"10°","azimuth":"295° (西北偏西)","distance":"1,508","brightness":"0.3","sunAltitude":"-19.0°"},"highestPoint":{"time":"20:15:08","altitude":"42°","azimuth":"223° (西南)","distance":"613","brightness":"-2.8","sunAltitude":"-19.6°"},"enterShadow":{"time":"20:15:40","altitude":"38°","azimuth":"196° (西南偏南)","distance":"654","brightness":"-2.9","sunAltitude":"-19.7°"},"dropBelowAltitude10deg":{"time":"20:18:19","altitude":"10°","azimuth":"151° (东南偏南)","distance":"1,495","brightness":"-","sunAltitude":"-20.2°"},"set":{"time":"20:20:28","altitude":"0°","azimuth":"144° (东南)","distance":"2,354","brightness":"-","sunAltitude":"-20.6°"}},"passType":"可见","image":"https://www.heavens-above.com/PassSkyChart2.ashx?passID=362853&size=800&lat=39.9042&lng=116.4074&loc=%e5%8c%97%e4%ba%ac%e5%b8%82&alt=52&tz=ChST&showUnlit=true","scoreData":[20,-2.8,-19.6,42],"exist":225,"score":71,"id":"492fc1ba301aa6ef40615ae1f3cfa486"},{"url":"https://www.heavens-above.com/passdetails.aspx?lat=39.9042&lng=116.4074&loc=%e5%8c%97%e4%ba%ac%e5%b8%82&alt=52&tz=ChST&satid=25544&mjd=61126.4759756135&type=A","date":"3月27日","brightness":"-2.9","events":{"rise":{"time":"19:19:59","altitude":"0°","azimuth":"311° (西北)","distance":"2,380","brightness":"1.2","sunAltitude":"-9.7°"},"reachAltitude10deg":{"time":"19:22:12","altitude":"10°","azimuth":"320° (西北)","distance":"1,511","brightness":"-0.1","sunAltitude":"-10.1°"},"highestPoint":{"time":"19:25:24","altitude":"38°","azimuth":"30° (东北偏北)","distance":"660","brightness":"-2.9","sunAltitude":"-10.7°"},"enterShadow":{"time":"19:27:34","altitude":"17°","azimuth":"93° (东)","distance":"1,133","brightness":"-2.2","sunAltitude":"-11.1°"},"dropBelowAltitude10deg":{"time":"19:28:35","altitude":"10°","azimuth":"101° (东)","distance":"1,501","brightness":"-","sunAltitude":"-11.3°"},"set":{"time":"19:30:45","altitude":"0°","azimuth":"110° (东南偏东)","distance":"2,362","brightness":"-","sunAltitude":"-11.7°"}},"passType":"可见","image":"https://www.heavens-above.com/PassSkyChart2.ashx?passID=362605&size=800&lat=39.9042&lng=116.4074&loc=%e5%8c%97%e4%ba%ac%e5%b8%82&alt=52&tz=ChST&showUnlit=true","scoreData":[19,-2.9,-10.7,38],"exist":322,"score":67,"id":"fe0714f52738908f612d1cdc35aba495"},{"url":"https://www.heavens-above.com/passdetails.aspx?lat=39.9042&lng=116.4074&loc=%e5%8c%97%e4%ba%ac%e5%b8%82&alt=52&tz=ChST&satid=25544&mjd=61151.8200854772&type=A","date":"4月22日","brightness":"-3.9","events":{"rise":{"time":"03:35:29","altitude":"0°","azimuth":"234° (西南)","distance":"2,349","brightness":"-","sunAltitude":"-20.0°"},"reachAltitude10deg":{"time":"03:37:34","altitude":"10°","azimuth":"235° (西南)","distance":"1,490","brightness":"-","sunAltitude":"-19.7°"},"exitShadow":{"time":"03:40:42","altitude":"74°","azimuth":"271° (西)","distance":"437","brightness":"-3.9","sunAltitude":"-19.2°"},"highestPoint":{"time":"03:40:54","altitude":"80°","azimuth":"322° (西北)","distance":"428","brightness":"-3.9","sunAltitude":"-19.1°"},"dropBelowAltitude10deg":{"time":"03:44:17","altitude":"10°","azimuth":"51° (东北)","distance":"1,500","brightness":"0.3","sunAltitude":"-18.6°"},"set":{"time":"03:46:23","altitude":"0°","azimuth":"52° (东北)","distance":"2,367","brightness":"1.8","sunAltitude":"-18.3°"}},"passType":"可见","image":"https://www.heavens-above.com/PassSkyChart2.ashx?passID=363041&size=800&lat=39.9042&lng=116.4074&loc=%e5%8c%97%e4%ba%ac%e5%b8%82&alt=52&tz=ChST&showUnlit=true","scoreData":[3,-3.9,-19.1,80],"exist":215,"score":62,"id":"de37a506ec0ee3046fd5a9d560254861"},{"url":"https://www.heavens-above.com/passdetails.aspx?lat=39.9042&lng=116.4074&loc=%e5%8c%97%e4%ba%ac%e5%b8%82&alt=52&tz=ChST&satid=25544&mjd=61130.4794558297&type=A","date":"3月31日","brightness":"-1.6","events":{"rise":{"time":"19:25:17","altitude":"0°","azimuth":"296° (西北偏西)","distance":"2,376","brightness":"2.0","sunAltitude":"-9.9°"},"reachAltitude10deg":{"time":"19:27:39","altitude":"10°","azimuth":"282° (西北偏西)","distance":"1,506","brightness":"0.7","sunAltitude":"-10.3°"},"highestPoint":{"time":"19:30:24","altitude":"23°","azimuth":"227° (西南)","distance":"931","brightness":"-1.6","sunAltitude":"-10.8°"},"dropBelowAltitude10deg":{"time":"19:33:09","altitude":"10°","azimuth":"172° (南)","distance":"1,495","brightness":"-1.2","sunAltitude":"-11.4°"},"enterShadow":{"time":"19:34:25","altitude":"4°","azimuth":"163° (东南偏南)","distance":"1,945","brightness":"-0.7","sunAltitude":"-11.6°"},"set":{"time":"19:35:29","altitude":"0°","azimuth":"158° (东南偏南)","distance":"2,353","brightness":"-","sunAltitude":"-11.8°"}},"passType":"可见","image":"https://www.heavens-above.com/PassSkyChart2.ashx?passID=362868&size=800&lat=39.9042&lng=116.4074&loc=%e5%8c%97%e4%ba%ac%e5%b8%82&alt=52&tz=ChST&showUnlit=true","scoreData":[19,-1.6,-10.8,23],"exist":406,"score":61,"id":"ae2f942a755ccc3714071ce1038fd52c"},{"url":"https://www.heavens-above.com/passdetails.aspx?lat=39.9042&lng=116.4074&loc=%e5%8c%97%e4%ba%ac%e5%b8%82&alt=52&tz=ChST&satid=25544&mjd=61123.5066481668&type=A","date":"3月24日","brightness":"-2.2","events":{"rise":{"time":"20:04:19","altitude":"0°","azimuth":"313° (西北)","distance":"2,380","brightness":"1.3","sunAltitude":"-18.5°"},"reachAltitude10deg":{"time":"20:06:39","altitude":"10°","azimuth":"327° (西北偏北)","distance":"1,512","brightness":"-0.2","sunAltitude":"-19.0°"},"highestPoint":{"time":"20:09:34","altitude":"26°","azimuth":"26° (东北偏北)","distance":"876","brightness":"-2.2","sunAltitude":"-19.5°"},"enterShadow":{"time":"20:09:34","altitude":"26°","azimuth":"26° (东北偏北)","distance":"876","brightness":"-2.2","sunAltitude":"-19.5°"},"dropBelowAltitude10deg":{"time":"20:12:28","altitude":"10°","azimuth":"85° (东)","distance":"1,503","brightness":"-","sunAltitude":"-20.0°"},"set":{"time":"20:14:47","altitude":"0°","azimuth":"98° (东)","distance":"2,364","brightness":"-","sunAltitude":"-20.4°"}},"passType":"可见","image":"https://www.heavens-above.com/PassSkyChart2.ashx?passID=362570&size=800&lat=39.9042&lng=116.4074&loc=%e5%8c%97%e4%ba%ac%e5%b8%82&alt=52&tz=ChST&showUnlit=true","scoreData":[20,-2.2,-19.5,26],"exist":175,"score":60,"id":"0a81272535b4087c7ed06296fee2b34e"},{"url":"https://www.heavens-above.com/passdetails.aspx?lat=39.9042&lng=116.4074&loc=%e5%8c%97%e4%ba%ac%e5%b8%82&alt=52&tz=ChST&satid=25544&mjd=61165.8270390962&type=A","date":"5月6日","brightness":"-2.2","events":{"rise":{"time":"03:45:34","altitude":"0°","azimuth":"312° (西北)","distance":"2,363","brightness":"-0.1","sunAltitude":"-14.8°"},"reachAltitude10deg":{"time":"03:47:46","altitude":"10°","azimuth":"320° (西北)","distance":"1,497","brightness":"-1.0","sunAltitude":"-14.4°"},"highestPoint":{"time":"03:50:55","altitude":"38°","azimuth":"30° (东北偏北)","distance":"658","brightness":"-2.2","sunAltitude":"-13.9°"},"dropBelowAltitude10deg":{"time":"03:54:05","altitude":"10°","azimuth":"101° (东)","distance":"1,491","brightness":"-0.3","sunAltitude":"-13.4°"},"set":{"time":"03:56:16","altitude":"0°","azimuth":"109° (东南偏东)","distance":"2,352","brightness":"0.6","sunAltitude":"-13.1°"}},"passType":"可见","image":"https://www.heavens-above.com/PassSkyChart2.ashx?passID=363255&size=800&lat=39.9042&lng=116.4074&loc=%e5%8c%97%e4%ba%ac%e5%b8%82&alt=52&tz=ChST&showUnlit=true","scoreData":[3,-2.2,-13.9,38],"exist":379,"score":58,"id":"a4cef7f0484df1f301d9743a9fc1d513"},{"url":"https://www.heavens-above.com/passdetails.aspx?lat=39.9042&lng=116.4074&loc=%e5%8c%97%e4%ba%ac%e5%b8%82&alt=52&tz=ChST&satid=25544&mjd=61148.8521842638&type=A","date":"4月19日","brightness":"-3.4","events":{"rise":{"time":"04:21:45","altitude":"0°","azimuth":"222° (西南)","distance":"2,348","brightness":"-","sunAltitude":"-13.3°"},"reachAltitude10deg":{"time":"04:23:51","altitude":"10°","azimuth":"219° (西南)","distance":"1,489","brightness":"-","sunAltitude":"-12.9°"},"exitShadow":{"time":"04:24:57","altitude":"19°","azimuth":"214° (西南偏南)","distance":"1,057","brightness":"-2.2","sunAltitude":"-12.8°"},"highestPoint":{"time":"04:27:08","altitude":"58°","azimuth":"139° (东南)","distance":"492","brightness":"-3.4","sunAltitude":"-12.4°"},"dropBelowAltitude10deg":{"time":"04:30:27","altitude":"10°","azimuth":"59° (东北偏东)","distance":"1,500","brightness":"0.6","sunAltitude":"-11.8°"},"set":{"time":"04:32:34","altitude":"0°","azimuth":"56° (东北)","distance":"2,368","brightness":"2.1","sunAltitude":"-11.4°"}},"passType":"可见","image":"https://www.heavens-above.com/PassSkyChart2.ashx?passID=362889&size=800&lat=39.9042&lng=116.4074&loc=%e5%8c%97%e4%ba%ac%e5%b8%82&alt=52&tz=ChST&showUnlit=true","scoreData":[4,-3.4,-12.4,58],"exist":330,"score":58,"id":"197ca0afb0b59b0f3cef9805780c17af"},{"url":"https://www.heavens-above.com/passdetails.aspx?lat=39.9042&lng=116.4074&loc=%e5%8c%97%e4%ba%ac%e5%b8%82&alt=52&tz=ChST&satid=25544&mjd=61164.8604336991&type=A","date":"5月5日","brightness":"-3.2","events":{"rise":{"time":"04:33:34","altitude":"0°","azimuth":"309° (西北)","distance":"2,363","brightness":"-0.2","sunAltitude":"-7.2°"},"reachAltitude10deg":{"time":"04:35:41","altitude":"10°","azimuth":"313° (西北)","distance":"1,497","brightness":"-1.1","sunAltitude":"-6.9°"},"highestPoint":{"time":"04:39:01","altitude":"62°","azimuth":"35° (东北)","distance":"474","brightness":"-3.2","sunAltitude":"-6.3°"},"dropBelowAltitude10deg":{"time":"04:42:20","altitude":"10°","azimuth":"117° (东南偏东)","distance":"1,490","brightness":"-0.4","sunAltitude":"-5.7°"},"set":{"time":"04:44:26","altitude":"0°","azimuth":"121° (东南偏东)","distance":"2,350","brightness":"0.5","sunAltitude":"-5.4°"}},"passType":"可见","image":"https://www.heavens-above.com/PassSkyChart2.ashx?passID=363297&size=800&lat=39.9042&lng=116.4074&loc=%e5%8c%97%e4%ba%ac%e5%b8%82&alt=52&tz=ChST&showUnlit=true","scoreData":[4,-3.2,-6.3,62],"exist":399,"score":56,"id":"4b1335f94e3545613662cedb5fe8945a"},{"url":"https://www.heavens-above.com/passdetails.aspx?lat=39.9042&lng=116.4074&loc=%e5%8c%97%e4%ba%ac%e5%b8%82&alt=52&tz=ChST&satid=25544&mjd=61150.853213886&type=A","date":"4月21日","brightness":"-3.2","events":{"rise":{"time":"04:23:14","altitude":"0°","azimuth":"245° (西南偏西)","distance":"2,352","brightness":"-","sunAltitude":"-12.5°"},"reachAltitude10deg":{"time":"04:25:22","altitude":"10°","azimuth":"251° (西南偏西)","distance":"1,492","brightness":"-","sunAltitude":"-12.1°"},"exitShadow":{"time":"04:26:32","altitude":"19°","azimuth":"259° (西)","distance":"1,055","brightness":"-2.3","sunAltitude":"-11.9°"},"highestPoint":{"time":"04:28:37","altitude":"47°","azimuth":"327° (西北偏北)","distance":"562","brightness":"-3.2","sunAltitude":"-11.6°"},"dropBelowAltitude10deg":{"time":"04:31:54","altitude":"10°","azimuth":"43° (东北)","distance":"1,501","brightness":"0.3","sunAltitude":"-11.0°"},"set":{"time":"04:34:03","altitude":"0°","azimuth":"50° (东北)","distance":"2,368","brightness":"1.8","sunAltitude":"-10.6°"}},"passType":"可见","image":"https://www.heavens-above.com/PassSkyChart2.ashx?passID=363121&size=800&lat=39.9042&lng=116.4074&loc=%e5%8c%97%e4%ba%ac%e5%b8%82&alt=52&tz=ChST&showUnlit=true","scoreData":[4,-3.2,-11.6,47],"exist":322,"score":56,"id":"0c636811b49a0822d9a47395eb194b0a"},{"url":"https://www.heavens-above.com/passdetails.aspx?lat=39.9042&lng=116.4074&loc=%e5%8c%97%e4%ba%ac%e5%b8%82&alt=52&tz=ChST&satid=25544&mjd=61124.4738786226&type=A","date":"3月25日","brightness":"-1.8","events":{"rise":{"time":"19:17:18","altitude":"0°","azimuth":"313° (西北)","distance":"2,381","brightness":"1.1","sunAltitude":"-9.6°"},"reachAltitude10deg":{"time":"19:19:49","altitude":"10°","azimuth":"332° (西北偏北)","distance":"1,513","brightness":"-0.4","sunAltitude":"-10.1°"},"highestPoint":{"time":"19:22:23","altitude":"20°","azimuth":"21° (东北偏北)","distance":"1,058","brightness":"-1.8","sunAltitude":"-10.6°"},"enterShadow":{"time":"19:24:32","altitude":"12°","azimuth":"65° (东北偏东)","distance":"1,393","brightness":"-1.6","sunAltitude":"-11.0°"},"dropBelowAltitude10deg":{"time":"19:24:56","altitude":"10°","azimuth":"70° (东北偏东)","distance":"1,506","brightness":"-","sunAltitude":"-11.0°"},"set":{"time":"19:27:26","altitude":"0°","azimuth":"88° (东)","distance":"2,367","brightness":"-","sunAltitude":"-11.5°"}},"passType":"可见","image":"https://www.heavens-above.com/PassSkyChart2.ashx?passID=362550&size=800&lat=39.9042&lng=116.4074&loc=%e5%8c%97%e4%ba%ac%e5%b8%82&alt=52&tz=ChST&showUnlit=true","scoreData":[19,-1.8,-10.6,20],"exist":283,"score":55,"id":"800378a25495ad0fb153171c97893c4d"},{"url":"https://www.heavens-above.com/passdetails.aspx?lat=39.9042&lng=116.4074&loc=%e5%8c%97%e4%ba%ac%e5%b8%82&alt=52&tz=ChST&satid=25544&mjd=61129.5120855036&type=A","date":"3月30日","brightness":"-1.0","events":{"rise":{"time":"20:12:43","altitude":"0°","azimuth":"290° (西北偏西)","distance":"2,374","brightness":"1.8","sunAltitude":"-18.7°"},"reachAltitude10deg":{"time":"20:15:35","altitude":"10°","azimuth":"263° (西)","distance":"1,503","brightness":"-0.1","sunAltitude":"-19.3°"},"highestPoint":{"time":"20:17:24","altitude":"14°","azimuth":"231° (西南)","distance":"1,285","brightness":"-1.0","sunAltitude":"-19.6°"},"enterShadow":{"time":"20:19:05","altitude":"10°","azimuth":"200° (西南偏南)","distance":"1,470","brightness":"-1.0","sunAltitude":"-19.9°"},"dropBelowAltitude10deg":{"time":"20:19:12","altitude":"10°","azimuth":"198° (西南偏南)","distance":"1,495","brightness":"-","sunAltitude":"-19.9°"},"set":{"time":"20:22:03","altitude":"0°","azimuth":"171° (南)","distance":"2,352","brightness":"-","sunAltitude":"-20.4°"}},"passType":"可见","image":"https://www.heavens-above.com/PassSkyChart2.ashx?passID=362867&size=800&lat=39.9042&lng=116.4074&loc=%e5%8c%97%e4%ba%ac%e5%b8%82&alt=52&tz=ChST&showUnlit=true","scoreData":[20,-1,-19.6,14],"exist":210,"score":55,"id":"925b5031fc3bbf93b71d7d78c9b756d5"},{"url":"https://www.heavens-above.com/passdetails.aspx?lat=39.9042&lng=116.4074&loc=%e5%8c%97%e4%ba%ac%e5%b8%82&alt=52&tz=ChST&satid=25544&mjd=61149.8191621118&type=A","date":"4月20日","brightness":"-2.6","events":{"rise":{"time":"03:34:22","altitude":"0°","azimuth":"210° (西南偏南)","distance":"2,346","brightness":"-","sunAltitude":"-20.8°"},"reachAltitude10deg":{"time":"03:36:34","altitude":"10°","azimuth":"200° (西南偏南)","distance":"1,487","brightness":"-","sunAltitude":"-20.4°"},"exitShadow":{"time":"03:39:19","altitude":"31°","azimuth":"146° (东南)","distance":"749","brightness":"-2.6","sunAltitude":"-20.0°"},"highestPoint":{"time":"03:39:35","altitude":"32°","azimuth":"135° (东南)","distance":"740","brightness":"-2.5","sunAltitude":"-19.9°"},"dropBelowAltitude10deg":{"time":"03:42:38","altitude":"10°","azimuth":"70° (东北偏东)","distance":"1,498","brightness":"0.2","sunAltitude":"-19.5°"},"set":{"time":"03:44:51","altitude":"0°","azimuth":"60° (东北偏东)","distance":"2,366","brightness":"1.7","sunAltitude":"-19.1°"}},"passType":"可见","image":"https://www.heavens-above.com/PassSkyChart2.ashx?passID=362912&size=800&lat=39.9042&lng=116.4074&loc=%e5%8c%97%e4%ba%ac%e5%b8%82&alt=52&tz=ChST&showUnlit=true","scoreData":[3,-2.5,-19.9,32],"exist":199,"score":54,"id":"0662446862d0803df677ded8a11d4e91"},{"url":"https://www.heavens-above.com/passdetails.aspx?lat=39.9042&lng=116.4074&loc=%e5%8c%97%e4%ba%ac%e5%b8%82&alt=52&tz=ChST&satid=25544&mjd=61153.8210882014&type=A","date":"4月24日","brightness":"-2.5","events":{"rise":{"time":"03:37:05","altitude":"0°","azimuth":"256° (西南偏西)","distance":"2,353","brightness":"-","sunAltitude":"-19.2°"},"reachAltitude10deg":{"time":"03:39:19","altitude":"10°","azimuth":"267° (西)","distance":"1,493","brightness":"-","sunAltitude":"-18.8°"},"exitShadow":{"time":"03:41:44","altitude":"29°","azimuth":"309° (西北)","distance":"804","brightness":"-2.5","sunAltitude":"-18.4°"},"highestPoint":{"time":"03:42:21","altitude":"31°","azimuth":"332° (西北偏北)","distance":"759","brightness":"-2.4","sunAltitude":"-18.3°"},"dropBelowAltitude10deg":{"time":"03:45:25","altitude":"10°","azimuth":"37° (东北)","distance":"1,500","brightness":"0.2","sunAltitude":"-17.9°"},"set":{"time":"03:47:40","altitude":"0°","azimuth":"48° (东北)","distance":"2,367","brightness":"1.7","sunAltitude":"-17.5°"}},"passType":"可见","image":"https://www.heavens-above.com/PassSkyChart2.ashx?passID=363106&size=800&lat=39.9042&lng=116.4074&loc=%e5%8c%97%e4%ba%ac%e5%b8%82&alt=52&tz=ChST&showUnlit=true","scoreData":[3,-2.4,-18.3,31],"exist":221,"score":52,"id":"d29c292b8227ccfdc9ecb9601c320a32"},{"url":"https://www.heavens-above.com/passdetails.aspx?lat=39.9042&lng=116.4074&loc=%e5%8c%97%e4%ba%ac%e5%b8%82&alt=52&tz=ChST&satid=25544&mjd=61164.7928545434&type=A","date":"5月5日","brightness":"-0.7","events":{"rise":{"time":"02:56:51","altitude":"0°","azimuth":"313° (西北)","distance":"2,363","brightness":"-","sunAltitude":"-22.0°"},"exitShadow":{"time":"02:57:18","altitude":"1°","azimuth":"316° (西北)","distance":"2,206","brightness":"-0.1","sunAltitude":"-21.9°"},"reachAltitude10deg":{"time":"02:59:35","altitude":"10°","azimuth":"337° (西北偏北)","distance":"1,498","brightness":"-0.7","sunAltitude":"-21.6°"},"highestPoint":{"time":"03:01:43","altitude":"16°","azimuth":"16° (东北偏北)","distance":"1,202","brightness":"-0.7","sunAltitude":"-21.3°"},"dropBelowAltitude10deg":{"time":"03:03:50","altitude":"10°","azimuth":"56° (东北)","distance":"1,496","brightness":"0.2","sunAltitude":"-21.0°"},"set":{"time":"03:06:33","altitude":"0°","azimuth":"80° (东)","distance":"2,358","brightness":"1.0","sunAltitude":"-20.7°"}},"passType":"可见","image":"https://www.heavens-above.com/PassSkyChart2.ashx?passID=363207&size=800&lat=39.9042&lng=116.4074&loc=%e5%8c%97%e4%ba%ac%e5%b8%82&alt=52&tz=ChST&showUnlit=true","scoreData":[3,-0.7,-21.3,16],"exist":392,"score":51,"id":"326eff80be1e7686a15507bd17b92465"},{"url":"https://www.heavens-above.com/passdetails.aspx?lat=39.9042&lng=116.4074&loc=%e5%8c%97%e4%ba%ac%e5%b8%82&alt=52&tz=ChST&satid=25544&mjd=61121.5043747809&type=A","date":"3月22日","brightness":"-1.5","events":{"rise":{"time":"20:01:25","altitude":"0°","azimuth":"313° (西北)","distance":"2,381","brightness":"1.2","sunAltitude":"-18.4°"},"reachAltitude10deg":{"time":"20:04:10","altitude":"10°","azimuth":"337° (西北偏北)","distance":"1,513","brightness":"-0.4","sunAltitude":"-18.9°"},"highestPoint":{"time":"20:06:17","altitude":"15°","azimuth":"16° (东北偏北)","distance":"1,221","brightness":"-1.4","sunAltitude":"-19.3°"},"enterShadow":{"time":"20:06:41","altitude":"15°","azimuth":"24° (东北偏北)","distance":"1,231","brightness":"-1.5","sunAltitude":"-19.4°"},"dropBelowAltitude10deg":{"time":"20:08:24","altitude":"10°","azimuth":"54° (东北)","distance":"1,508","brightness":"-","sunAltitude":"-19.7°"},"set":{"time":"20:11:09","altitude":"0°","azimuth":"79° (东北偏东)","distance":"2,369","brightness":"-","sunAltitude":"-20.2°"}},"passType":"可见","image":"https://www.heavens-above.com/PassSkyChart2.ashx?passID=362589&size=800&lat=39.9042&lng=116.4074&loc=%e5%8c%97%e4%ba%ac%e5%b8%82&alt=52&tz=ChST&showUnlit=true","scoreData":[20,-1.4,-19.3,15],"exist":151,"score":51,"id":"07bbe9be6d8a16df4e179193dd37a323"},{"url":"https://www.heavens-above.com/passdetails.aspx?lat=39.9042&lng=116.4074&loc=%e5%8c%97%e4%ba%ac%e5%b8%82&alt=52&tz=ChST&satid=25544&mjd=61163.8263434958&type=A","date":"5月4日","brightness":"-1.0","events":{"rise":{"time":"03:44:53","altitude":"0°","azimuth":"314° (西北)","distance":"2,364","brightness":"0.0","sunAltitude":"-15.3°"},"reachAltitude10deg":{"time":"03:47:23","altitude":"10°","azimuth":"332° (西北偏北)","distance":"1,498","brightness":"-0.9","sunAltitude":"-15.0°"},"highestPoint":{"time":"03:49:56","altitude":"20°","azimuth":"21° (东北偏北)","distance":"1,043","brightness":"-1.0","sunAltitude":"-14.6°"},"dropBelowAltitude10deg":{"time":"03:52:28","altitude":"10°","azimuth":"71° (东北偏东)","distance":"1,495","brightness":"0.3","sunAltitude":"-14.2°"},"set":{"time":"03:54:57","altitude":"0°","azimuth":"89° (东)","distance":"2,357","brightness":"1.0","sunAltitude":"-13.8°"}},"passType":"可见","image":"https://www.heavens-above.com/PassSkyChart2.ashx?passID=363254&size=800&lat=39.9042&lng=116.4074&loc=%e5%8c%97%e4%ba%ac%e5%b8%82&alt=52&tz=ChST&showUnlit=true","scoreData":[3,-1,-14.6,20],"exist":305,"score":49,"id":"a30901dfd6df377c286a96b262beea3c"},{"url":"https://www.heavens-above.com/passdetails.aspx?lat=39.9042&lng=116.4074&loc=%e5%8c%97%e4%ba%ac%e5%b8%82&alt=52&tz=ChST&satid=25544&mjd=61162.8597792315&type=A","date":"5月3日","brightness":"-1.5","events":{"rise":{"time":"04:32:51","altitude":"0°","azimuth":"313° (西北)","distance":"2,364","brightness":"-0.1","sunAltitude":"-7.8°"},"reachAltitude10deg":{"time":"04:35:10","altitude":"10°","azimuth":"326° (西北)","distance":"1,498","brightness":"-1.0","sunAltitude":"-7.4°"},"highestPoint":{"time":"04:38:04","altitude":"27°","azimuth":"26° (东北偏北)","distance":"851","brightness":"-1.5","sunAltitude":"-6.9°"},"dropBelowAltitude10deg":{"time":"04:40:59","altitude":"10°","azimuth":"86° (东)","distance":"1,494","brightness":"0.3","sunAltitude":"-6.4°"},"set":{"time":"04:43:17","altitude":"0°","azimuth":"99° (东)","distance":"2,355","brightness":"1.1","sunAltitude":"-6.0°"}},"passType":"可见","image":"https://www.heavens-above.com/PassSkyChart2.ashx?passID=363202&size=800&lat=39.9042&lng=116.4074&loc=%e5%8c%97%e4%ba%ac%e5%b8%82&alt=52&tz=ChST&showUnlit=true","scoreData":[4,-1.5,-6.9,27],"exist":349,"score":48,"id":"623000c94d6f359b173e90d305fa8a42"},{"url":"https://www.heavens-above.com/passdetails.aspx?lat=39.9042&lng=116.4074&loc=%e5%8c%97%e4%ba%ac%e5%b8%82&alt=52&tz=ChST&satid=25544&mjd=61152.8543322515&type=A","date":"4月23日","brightness":"-1.9","events":{"rise":{"time":"04:25:07","altitude":"0°","azimuth":"266° (西)","distance":"2,356","brightness":"-","sunAltitude":"-11.6°"},"reachAltitude10deg":{"time":"04:27:31","altitude":"10°","azimuth":"282° (西北偏西)","distance":"1,496","brightness":"-","sunAltitude":"-11.2°"},"exitShadow":{"time":"04:27:43","altitude":"11°","azimuth":"284° (西北偏西)","distance":"1,430","brightness":"-1.5","sunAltitude":"-11.2°"},"highestPoint":{"time":"04:30:14","altitude":"22°","azimuth":"336° (西北偏北)","distance":"959","brightness":"-1.9","sunAltitude":"-10.7°"},"dropBelowAltitude10deg":{"time":"04:32:58","altitude":"10°","azimuth":"31° (东北偏北)","distance":"1,501","brightness":"0.0","sunAltitude":"-10.3°"},"set":{"time":"04:35:23","altitude":"0°","azimuth":"47° (东北)","distance":"2,368","brightness":"1.7","sunAltitude":"-9.9°"}},"passType":"可见","image":"https://www.heavens-above.com/PassSkyChart2.ashx?passID=363105&size=800&lat=39.9042&lng=116.4074&loc=%e5%8c%97%e4%ba%ac%e5%b8%82&alt=52&tz=ChST&showUnlit=true","scoreData":[4,-1.9,-10.7,22],"exist":315,"score":48,"id":"adcf774c97a8af9fbde1083b79573402"},{"url":"https://www.heavens-above.com/passdetails.aspx?lat=39.9042&lng=116.4074&loc=%e5%8c%97%e4%ba%ac%e5%b8%82&alt=52&tz=ChST&satid=25544&mjd=61146.8512433824&type=A","date":"4月17日","brightness":"-1.4","events":{"rise":{"time":"04:20:52","altitude":"0°","azimuth":"197° (西南偏南)","distance":"2,346","brightness":"-","sunAltitude":"-14.0°"},"exitShadow":{"time":"04:22:54","altitude":"8°","azimuth":"183° (南)","distance":"1,628","brightness":"-1.1","sunAltitude":"-13.7°"},"reachAltitude10deg":{"time":"04:23:21","altitude":"10°","azimuth":"178° (南)","distance":"1,488","brightness":"-1.2","sunAltitude":"-13.6°"},"highestPoint":{"time":"04:25:47","altitude":"19°","azimuth":"131° (东南)","distance":"1,071","brightness":"-1.4","sunAltitude":"-13.2°"},"dropBelowAltitude10deg":{"time":"04:28:13","altitude":"10°","azimuth":"85° (东)","distance":"1,498","brightness":"0.3","sunAltitude":"-12.8°"},"set":{"time":"04:30:44","altitude":"0°","azimuth":"66° (东北偏东)","distance":"2,366","brightness":"2.2","sunAltitude":"-12.3°"}},"passType":"可见","image":"https://www.heavens-above.com/PassSkyChart2.ashx?passID=362898&size=800&lat=39.9042&lng=116.4074&loc=%e5%8c%97%e4%ba%ac%e5%b8%82&alt=52&tz=ChST&showUnlit=true","scoreData":[4,-1.4,-13.2,19],"exist":319,"score":47,"id":"ee78b540e215264fc01111717d73e93c"},{"url":"https://www.heavens-above.com/passdetails.aspx?lat=39.9042&lng=116.4074&loc=%e5%8c%97%e4%ba%ac%e5%b8%82&alt=52&tz=ChST&satid=25544&mjd=61155.822170002&type=A","date":"4月26日","brightness":"-1.5","events":{"rise":{"time":"03:38:59","altitude":"0°","azimuth":"276° (西)","distance":"2,357","brightness":"-","sunAltitude":"-18.3°"},"reachAltitude10deg":{"time":"03:41:35","altitude":"10°","azimuth":"297° (西北偏西)","distance":"1,497","brightness":"-","sunAltitude":"-17.9°"},"exitShadow":{"time":"03:42:29","altitude":"14°","azimuth":"311° (西北)","distance":"1,278","brightness":"-1.5","sunAltitude":"-17.8°"},"highestPoint":{"time":"03:43:55","altitude":"17°","azimuth":"341° (西北偏北)","distance":"1,127","brightness":"-1.4","sunAltitude":"-17.5°"},"dropBelowAltitude10deg":{"time":"03:46:16","altitude":"10°","azimuth":"25° (东北偏北)","distance":"1,500","brightness":"0.0","sunAltitude":"-17.2°"},"set":{"time":"03:48:53","altitude":"0°","azimuth":"46° (东北)","distance":"2,367","brightness":"1.8","sunAltitude":"-16.8°"}},"passType":"可见","image":"https://www.heavens-above.com/PassSkyChart2.ashx?passID=362980&size=800&lat=39.9042&lng=116.4074&loc=%e5%8c%97%e4%ba%ac%e5%b8%82&alt=52&tz=ChST&showUnlit=true","scoreData":[3,-1.4,-17.5,17],"exist":227,"score":47,"id":"6dd7baa5adeecfcea6f08c7154781ede"},{"url":"https://www.heavens-above.com/passdetails.aspx?lat=39.9042&lng=116.4074&loc=%e5%8c%97%e4%ba%ac%e5%b8%82&alt=52&tz=ChST&satid=25544&mjd=61122.4715859446&type=A","date":"3月23日","brightness":"-1.2","events":{"rise":{"time":"19:14:21","altitude":"0°","azimuth":"311° (西北)","distance":"2,381","brightness":"1.2","sunAltitude":"-9.5°"},"reachAltitude10deg":{"time":"19:17:22","altitude":"10°","azimuth":"340° (西北偏北)","distance":"1,514","brightness":"-0.5","sunAltitude":"-10.0°"},"highestPoint":{"time":"19:19:04","altitude":"13°","azimuth":"11° (北)","distance":"1,331","brightness":"-1.2","sunAltitude":"-10.4°"},"dropBelowAltitude10deg":{"time":"19:20:47","altitude":"10°","azimuth":"41° (东北)","distance":"1,510","brightness":"-1.2","sunAltitude":"-10.7°"},"enterShadow":{"time":"19:21:37","altitude":"7°","azimuth":"52° (东北)","distance":"1,704","brightness":"-1.1","sunAltitude":"-10.8°"},"set":{"time":"19:23:47","altitude":"0°","azimuth":"70° (东北偏东)","distance":"2,372","brightness":"-","sunAltitude":"-11.2°"}},"passType":"可见","image":"https://www.heavens-above.com/PassSkyChart2.ashx?passID=362566&size=800&lat=39.9042&lng=116.4074&loc=%e5%8c%97%e4%ba%ac%e5%b8%82&alt=52&tz=ChST&showUnlit=true","scoreData":[19,-1.2,-10.4,13],"exist":255,"score":46,"id":"3520d03102ccef332a3162a095686597"},{"url":"https://www.heavens-above.com/passdetails.aspx?lat=39.9042&lng=116.4074&loc=%e5%8c%97%e4%ba%ac%e5%b8%82&alt=52&tz=ChST&satid=25544&mjd=61118.4666216554&type=A","date":"3月19日","brightness":"-1.0","events":{"rise":{"time":"19:07:12","altitude":"0°","azimuth":"290° (西北偏西)","distance":"2,380","brightness":"2.0","sunAltitude":"-8.9°"},"reachAltitude10deg":{"time":"19:10:14","altitude":"10°","azimuth":"319° (西北)","distance":"1,514","brightness":"-0.2","sunAltitude":"-9.5°"},"highestPoint":{"time":"19:11:56","altitude":"13°","azimuth":"349° (北)","distance":"1,336","brightness":"-1.0","sunAltitude":"-9.8°"},"dropBelowAltitude10deg":{"time":"19:13:38","altitude":"10°","azimuth":"20° (东北偏北)","distance":"1,514","brightness":"-1.0","sunAltitude":"-10.1°"},"enterShadow":{"time":"19:15:45","altitude":"3°","azimuth":"43° (东北)","distance":"2,080","brightness":"-0.6","sunAltitude":"-10.5°"},"set":{"time":"19:16:39","altitude":"0°","azimuth":"49° (东北)","distance":"2,378","brightness":"-","sunAltitude":"-10.7°"}},"passType":"可见","image":"https://www.heavens-above.com/PassSkyChart2.ashx?passID=362585&size=800&lat=39.9042&lng=116.4074&loc=%e5%8c%97%e4%ba%ac%e5%b8%82&alt=52&tz=ChST&showUnlit=true","scoreData":[19,-1,-9.8,13],"exist":331,"score":45,"id":"d64a93cd8383d288aba744495337e2e2"},{"url":"https://www.heavens-above.com/passdetails.aspx?lat=39.9042&lng=116.4074&loc=%e5%8c%97%e4%ba%ac%e5%b8%82&alt=52&tz=ChST&satid=25544&mjd=61165.759327639&type=A","date":"5月6日","brightness":"-0.5","events":{"rise":{"time":"02:08:44","altitude":"0°","azimuth":"312° (西北)","distance":"2,363","brightness":"-","sunAltitude":"-27.4°"},"exitShadow":{"time":"02:10:58","altitude":"7°","azimuth":"331° (西北偏北)","distance":"1,676","brightness":"-0.4","sunAltitude":"-27.1°"},"reachAltitude10deg":{"time":"02:11:44","altitude":"10°","azimuth":"341° (西北偏北)","distance":"1,498","brightness":"-0.5","sunAltitude":"-27.1°"},"highestPoint":{"time":"02:13:25","altitude":"13°","azimuth":"11° (北)","distance":"1,321","brightness":"-0.5","sunAltitude":"-26.9°"},"dropBelowAltitude10deg":{"time":"02:15:06","altitude":"10°","azimuth":"41° (东北)","distance":"1,497","brightness":"0.0","sunAltitude":"-26.7°"},"set":{"time":"02:18:06","altitude":"0°","azimuth":"71° (东北偏东)","distance":"2,360","brightness":"0.8","sunAltitude":"-26.4°"}},"passType":"可见","image":"https://www.heavens-above.com/PassSkyChart2.ashx?passID=363268&size=800&lat=39.9042&lng=116.4074&loc=%e5%8c%97%e4%ba%ac%e5%b8%82&alt=52&tz=ChST&showUnlit=true","scoreData":[2,-0.5,-26.9,13],"exist":248,"score":43,"id":"1fca0260a145a25d3fc8fec68bf49435"},{"url":"https://www.heavens-above.com/passdetails.aspx?lat=39.9042&lng=116.4074&loc=%e5%8c%97%e4%ba%ac%e5%b8%82&alt=52&tz=ChST&satid=25544&mjd=61119.5019184518&type=A","date":"3月20日","brightness":"-1.1","events":{"rise":{"time":"19:58:09","altitude":"0°","azimuth":"308° (西北)","distance":"2,381","brightness":"1.3","sunAltitude":"-18.3°"},"reachAltitude10deg":{"time":"20:01:25","altitude":"10°","azimuth":"342° (西北偏北)","distance":"1,514","brightness":"-0.5","sunAltitude":"-18.9°"},"highestPoint":{"time":"20:02:46","altitude":"12°","azimuth":"5° (北)","distance":"1,406","brightness":"-1.0","sunAltitude":"-19.1°"},"enterShadow":{"time":"20:03:45","altitude":"11°","azimuth":"23° (东北偏北)","distance":"1,465","brightness":"-1.1","sunAltitude":"-19.3°"},"dropBelowAltitude10deg":{"time":"20:04:06","altitude":"10°","azimuth":"28° (东北偏北)","distance":"1,511","brightness":"-","sunAltitude":"-19.4°"},"set":{"time":"20:07:21","altitude":"0°","azimuth":"62° (东北偏东)","distance":"2,373","brightness":"-","sunAltitude":"-20.0°"}},"passType":"可见","image":"https://www.heavens-above.com/PassSkyChart2.ashx?passID=362805&size=800&lat=39.9042&lng=116.4074&loc=%e5%8c%97%e4%ba%ac%e5%b8%82&alt=52&tz=ChST&showUnlit=true","scoreData":[20,-1,-19.1,12],"exist":140,"score":43,"id":"f133a05ab6e7b2ebd17a3fd52707017f"},{"url":"https://www.heavens-above.com/passdetails.aspx?lat=39.9042&lng=116.4074&loc=%e5%8c%97%e4%ba%ac%e5%b8%82&alt=52&tz=ChST&satid=25544&mjd=61161.757448815&type=A","date":"5月2日","brightness":"-0.7","events":{"rise":{"time":"02:06:06","altitude":"0°","azimuth":"292° (西北偏西)","distance":"2,360","brightness":"-","sunAltitude":"-28.7°"},"reachAltitude10deg":{"time":"02:09:12","altitude":"10°","azimuth":"324° (西北)","distance":"1,498","brightness":"-","sunAltitude":"-28.4°"},"exitShadow":{"time":"02:10:39","altitude":"12°","azimuth":"349° (北)","distance":"1,356","brightness":"-0.7","sunAltitude":"-28.3°"},"highestPoint":{"time":"02:10:44","altitude":"12°","azimuth":"351° (北)","distance":"1,356","brightness":"-0.7","sunAltitude":"-28.3°"},"dropBelowAltitude10deg":{"time":"02:12:15","altitude":"10°","azimuth":"18° (东北偏北)","distance":"1,499","brightness":"-0.1","sunAltitude":"-28.1°"},"set":{"time":"02:15:22","altitude":"0°","azimuth":"49° (东北)","distance":"2,364","brightness":"1.2","sunAltitude":"-27.8°"}},"passType":"可见","image":"https://www.heavens-above.com/PassSkyChart2.ashx?passID=363197&size=800&lat=39.9042&lng=116.4074&loc=%e5%8c%97%e4%ba%ac%e5%b8%82&alt=52&tz=ChST&showUnlit=true","scoreData":[2,-0.7,-28.3,12],"exist":96,"score":42,"id":"47c5deaa25d5afc98fa65a75b591772a"},{"url":"https://www.heavens-above.com/passdetails.aspx?lat=39.9042&lng=116.4074&loc=%e5%8c%97%e4%ba%ac%e5%b8%82&alt=52&tz=ChST&satid=25544&mjd=61154.8555191199&type=A","date":"4月25日","brightness":"-1.2","events":{"rise":{"time":"04:27:10","altitude":"0°","azimuth":"285° (西北偏西)","distance":"2,360","brightness":"-","sunAltitude":"-10.7°"},"exitShadow":{"time":"04:28:36","altitude":"5°","azimuth":"295° (西北偏西)","distance":"1,885","brightness":"-0.8","sunAltitude":"-10.5°"},"reachAltitude10deg":{"time":"04:30:01","altitude":"10°","azimuth":"311° (西北)","distance":"1,499","brightness":"-1.2","sunAltitude":"-10.2°"},"highestPoint":{"time":"04:31:56","altitude":"14°","azimuth":"346° (西北偏北)","distance":"1,266","brightness":"-1.2","sunAltitude":"-9.9°"},"dropBelowAltitude10deg":{"time":"04:33:51","altitude":"10°","azimuth":"21° (东北偏北)","distance":"1,501","brightness":"-0.2","sunAltitude":"-9.6°"},"set":{"time":"04:36:43","altitude":"0°","azimuth":"47° (东北)","distance":"2,367","brightness":"1.8","sunAltitude":"-9.1°"}},"passType":"可见","image":"https://www.heavens-above.com/PassSkyChart2.ashx?passID=362963&size=800&lat=39.9042&lng=116.4074&loc=%e5%8c%97%e4%ba%ac%e5%b8%82&alt=52&tz=ChST&showUnlit=true","scoreData":[4,-1.2,-9.9,14],"exist":315,"score":41,"id":"275b93b98732d21b5922644bbcc1734d"},{"url":"https://www.heavens-above.com/passdetails.aspx?lat=39.9042&lng=116.4074&loc=%e5%8c%97%e4%ba%ac%e5%b8%82&alt=52&tz=ChST&satid=25544&mjd=61117.4993606993&type=A","date":"3月18日","brightness":"-1.0","events":{"rise":{"time":"19:54:27","altitude":"0°","azimuth":"297° (西北偏西)","distance":"2,381","brightness":"1.6","sunAltitude":"-18.0°"},"reachAltitude10deg":{"time":"19:57:43","altitude":"10°","azimuth":"331° (西北偏北)","distance":"1,514","brightness":"-0.3","sunAltitude":"-18.6°"},"highestPoint":{"time":"19:59:04","altitude":"12°","azimuth":"354° (北)","distance":"1,403","brightness":"-0.9","sunAltitude":"-18.9°"},"dropBelowAltitude10deg":{"time":"20:00:26","altitude":"10°","azimuth":"18° (东北偏北)","distance":"1,513","brightness":"-1.0","sunAltitude":"-19.1°"},"enterShadow":{"time":"20:00:42","altitude":"9°","azimuth":"22° (东北偏北)","distance":"1,558","brightness":"-0.9","sunAltitude":"-19.2°"},"set":{"time":"20:03:41","altitude":"0°","azimuth":"52° (东北)","distance":"2,376","brightness":"-","sunAltitude":"-19.7°"}},"passType":"可见","image":"https://www.heavens-above.com/PassSkyChart2.ashx?passID=362529&size=800&lat=39.9042&lng=116.4074&loc=%e5%8c%97%e4%ba%ac%e5%b8%82&alt=52&tz=ChST&showUnlit=true","scoreData":[19,-0.9,-18.9,12],"exist":179,"score":41,"id":"d427c0ce8d361b7536fbae492ce670dd"},{"url":"https://www.heavens-above.com/passdetails.aspx?lat=39.9042&lng=116.4074&loc=%e5%8c%97%e4%ba%ac%e5%b8%82&alt=52&tz=ChST&satid=25544&mjd=61160.7909438523&type=A","date":"5月1日","brightness":"-0.7","events":{"rise":{"time":"02:54:24","altitude":"0°","azimuth":"299° (西北偏西)","distance":"2,361","brightness":"-","sunAltitude":"-23.3°"},"exitShadow":{"time":"02:57:01","altitude":"8°","azimuth":"324° (西北)","distance":"1,627","brightness":"-0.7","sunAltitude":"-23.0°"},"reachAltitude10deg":{"time":"02:57:45","altitude":"10°","azimuth":"335° (西北偏北)","distance":"1,499","brightness":"-0.7","sunAltitude":"-22.9°"},"highestPoint":{"time":"02:58:57","altitude":"11°","azimuth":"356° (北)","distance":"1,414","brightness":"-0.6","sunAltitude":"-22.7°"},"dropBelowAltitude10deg":{"time":"03:00:08","altitude":"10°","azimuth":"17° (东北偏北)","distance":"1,499","brightness":"-0.1","sunAltitude":"-22.6°"},"set":{"time":"03:03:30","altitude":"0°","azimuth":"53° (东北)","distance":"2,364","brightness":"1.5","sunAltitude":"-22.1°"}},"passType":"可见","image":"https://www.heavens-above.com/PassSkyChart2.ashx?passID=363170&size=800&lat=39.9042&lng=116.4074&loc=%e5%8c%97%e4%ba%ac%e5%b8%82&alt=52&tz=ChST&showUnlit=true","scoreData":[2,-0.6,-22.7,11],"exist":187,"score":40,"id":"47837abb0f6ac304436c2b929def429f"},{"url":"https://www.heavens-above.com/passdetails.aspx?lat=39.9042&lng=116.4074&loc=%e5%8c%97%e4%ba%ac%e5%b8%82&alt=52&tz=ChST&satid=25544&mjd=61158.7898788021&type=A","date":"4月29日","brightness":"-1.1","events":{"rise":{"time":"02:52:39","altitude":"0°","azimuth":"285° (西北偏西)","distance":"2,359","brightness":"-","sunAltitude":"-24.1°"},"reachAltitude10deg":{"time":"02:55:29","altitude":"10°","azimuth":"311° (西北)","distance":"1,497","brightness":"-","sunAltitude":"-23.8°"},"exitShadow":{"time":"02:56:45","altitude":"14°","azimuth":"332° (西北偏北)","distance":"1,292","brightness":"-1.1","sunAltitude":"-23.6°"},"highestPoint":{"time":"02:57:25","altitude":"14°","azimuth":"346° (西北偏北)","distance":"1,261","brightness":"-1.0","sunAltitude":"-23.5°"},"dropBelowAltitude10deg":{"time":"02:59:21","altitude":"10°","azimuth":"21° (东北偏北)","distance":"1,500","brightness":"-0.1","sunAltitude":"-23.2°"},"set":{"time":"03:02:12","altitude":"0°","azimuth":"47° (东北)","distance":"2,365","brightness":"1.6","sunAltitude":"-22.8°"}},"passType":"可见","image":"https://www.heavens-above.com/PassSkyChart2.ashx?passID=363204&size=800&lat=39.9042&lng=116.4074&loc=%e5%8c%97%e4%ba%ac%e5%b8%82&alt=52&tz=ChST&showUnlit=true","scoreData":[2,-1,-23.5,14],"exist":156,"score":39,"id":"7d6a03d4b663af1d8a26eae1bc618626"},{"url":"https://www.heavens-above.com/passdetails.aspx?lat=39.9042&lng=116.4074&loc=%e5%8c%97%e4%ba%ac%e5%b8%82&alt=52&tz=ChST&satid=25544&mjd=61120.4691369315&type=A","date":"3月21日","brightness":"-1.0","events":{"rise":{"time":"19:10:59","altitude":"0°","azimuth":"303° (西北偏西)","distance":"2,381","brightness":"1.4","sunAltitude":"-9.2°"},"reachAltitude10deg":{"time":"19:14:21","altitude":"10°","azimuth":"339° (西北偏北)","distance":"1,514","brightness":"-0.5","sunAltitude":"-9.9°"},"highestPoint":{"time":"19:15:33","altitude":"11°","azimuth":"0° (北)","distance":"1,428","brightness":"-0.9","sunAltitude":"-10.1°"},"dropBelowAltitude10deg":{"time":"19:16:45","altitude":"10°","azimuth":"21° (东北偏北)","distance":"1,513","brightness":"-1.0","sunAltitude":"-10.3°"},"enterShadow":{"time":"19:18:44","altitude":"4°","azimuth":"46° (东北)","distance":"1,946","brightness":"-0.7","sunAltitude":"-10.7°"},"set":{"time":"19:20:07","altitude":"0°","azimuth":"57° (东北偏东)","distance":"2,376","brightness":"-","sunAltitude":"-11.0°"}},"passType":"可见","image":"https://www.heavens-above.com/PassSkyChart2.ashx?passID=362634&size=800&lat=39.9042&lng=116.4074&loc=%e5%8c%97%e4%ba%ac%e5%b8%82&alt=52&tz=ChST&showUnlit=true","scoreData":[19,-0.9,-10.1,11],"exist":263,"score":38,"id":"494ffe53fe642fa4ddafee4d14faf59e"},{"url":"https://www.heavens-above.com/passdetails.aspx?lat=39.9042&lng=116.4074&loc=%e5%8c%97%e4%ba%ac%e5%b8%82&alt=52&tz=ChST&satid=25544&mjd=61160.8589172787&type=A","date":"5月1日","brightness":"-0.9","events":{"rise":{"time":"04:31:58","altitude":"0°","azimuth":"313° (西北)","distance":"2,364","brightness":"-0.1","sunAltitude":"-8.4°"},"reachAltitude10deg":{"time":"04:34:40","altitude":"10°","azimuth":"337° (西北偏北)","distance":"1,499","brightness":"-0.9","sunAltitude":"-7.9°"},"highestPoint":{"time":"04:36:50","altitude":"16°","azimuth":"17° (东北偏北)","distance":"1,193","brightness":"-0.8","sunAltitude":"-7.6°"},"dropBelowAltitude10deg":{"time":"04:38:59","altitude":"10°","azimuth":"57° (东北偏东)","distance":"1,498","brightness":"0.8","sunAltitude":"-7.2°"},"set":{"time":"04:41:42","altitude":"0°","azimuth":"80° (东)","distance":"2,360","brightness":"1.8","sunAltitude":"-6.7°"}},"passType":"可见","image":"https://www.heavens-above.com/PassSkyChart2.ashx?passID=363199&size=800&lat=39.9042&lng=116.4074&loc=%e5%8c%97%e4%ba%ac%e5%b8%82&alt=52&tz=ChST&showUnlit=true","scoreData":[4,-0.8,-7.6,16],"exist":259,"score":38,"id":"6d5fa875a9db1ab176f1c07fd36b521b"},{"url":"https://www.heavens-above.com/passdetails.aspx?lat=39.9042&lng=116.4074&loc=%e5%8c%97%e4%ba%ac%e5%b8%82&alt=52&tz=ChST&satid=25544&mjd=61159.824418877&type=A","date":"4月30日","brightness":"-0.7","events":{"rise":{"time":"03:42:38","altitude":"0°","azimuth":"305° (西北)","distance":"2,363","brightness":"-","sunAltitude":"-16.7°"},"exitShadow":{"time":"03:43:21","altitude":"2°","azimuth":"310° (西北)","distance":"2,131","brightness":"-0.3","sunAltitude":"-16.6°"},"reachAltitude10deg":{"time":"03:46:02","altitude":"10°","azimuth":"342° (西北偏北)","distance":"1,500","brightness":"-0.7","sunAltitude":"-16.2°"},"highestPoint":{"time":"03:47:09","altitude":"11°","azimuth":"1° (北)","distance":"1,425","brightness":"-0.6","sunAltitude":"-16.0°"},"dropBelowAltitude10deg":{"time":"03:48:16","altitude":"10°","azimuth":"21° (东北偏北)","distance":"1,500","brightness":"-0.1","sunAltitude":"-15.8°"},"set":{"time":"03:51:41","altitude":"0°","azimuth":"58° (东北偏东)","distance":"2,364","brightness":"2.0","sunAltitude":"-15.3°"}},"passType":"可见","image":"https://www.heavens-above.com/PassSkyChart2.ashx?passID=363215&size=800&lat=39.9042&lng=116.4074&loc=%e5%8c%97%e4%ba%ac%e5%b8%82&alt=52&tz=ChST&showUnlit=true","scoreData":[3,-0.6,-16,11],"exist":295,"score":37,"id":"60d0e7fcb9529130640ade22160c2743"},{"url":"https://www.heavens-above.com/passdetails.aspx?lat=39.9042&lng=116.4074&loc=%e5%8c%97%e4%ba%ac%e5%b8%82&alt=52&tz=ChST&satid=25544&mjd=61162.791956&type=A","date":"5月3日","brightness":"-0.6","events":{"rise":{"time":"02:55:50","altitude":"0°","azimuth":"309° (西北)","distance":"2,363","brightness":"-","sunAltitude":"-22.6°"},"exitShadow":{"time":"02:57:10","altitude":"4°","azimuth":"319° (西北)","distance":"1,942","brightness":"-0.3","sunAltitude":"-22.4°"},"reachAltitude10deg":{"time":"02:59:05","altitude":"10°","azimuth":"343° (西北偏北)","distance":"1,499","brightness":"-0.6","sunAltitude":"-22.2°"},"highestPoint":{"time":"03:00:25","altitude":"12°","azimuth":"6° (北)","distance":"1,393","brightness":"-0.4","sunAltitude":"-22.0°"},"dropBelowAltitude10deg":{"time":"03:01:44","altitude":"10°","azimuth":"30° (东北偏北)","distance":"1,499","brightness":"0.1","sunAltitude":"-21.8°"},"set":{"time":"03:04:59","altitude":"0°","azimuth":"64° (东北偏东)","distance":"2,362","brightness":"1.3","sunAltitude":"-21.4°"}},"passType":"可见","image":"https://www.heavens-above.com/PassSkyChart2.ashx?passID=363229&size=800&lat=39.9042&lng=116.4074&loc=%e5%8c%97%e4%ba%ac%e5%b8%82&alt=52&tz=ChST&showUnlit=true","scoreData":[3,-0.4,-22,12],"exist":274,"score":35,"id":"11baf158048eef64e017fccafd35fd0f"},{"url":"https://www.heavens-above.com/passdetails.aspx?lat=39.9042&lng=116.4074&loc=%e5%8c%97%e4%ba%ac%e5%b8%82&alt=52&tz=ChST&satid=25544&mjd=61157.82329784&type=A","date":"4月28日","brightness":"-1.0","events":{"rise":{"time":"03:40:55","altitude":"0°","azimuth":"293° (西北偏西)","distance":"2,361","brightness":"-","sunAltitude":"-17.5°"},"exitShadow":{"time":"03:43:01","altitude":"7°","azimuth":"311° (西北)","distance":"1,723","brightness":"-0.8","sunAltitude":"-17.1°"},"reachAltitude10deg":{"time":"03:44:02","altitude":"10°","azimuth":"324° (西北)","distance":"1,499","brightness":"-1.0","sunAltitude":"-17.0°"},"highestPoint":{"time":"03:45:33","altitude":"12°","azimuth":"351° (北)","distance":"1,360","brightness":"-0.8","sunAltitude":"-16.8°"},"dropBelowAltitude10deg":{"time":"03:47:03","altitude":"10°","azimuth":"18° (东北偏北)","distance":"1,500","brightness":"-0.2","sunAltitude":"-16.5°"},"set":{"time":"03:50:11","altitude":"0°","azimuth":"50° (东北)","distance":"2,366","brightness":"1.9","sunAltitude":"-16.0°"}},"passType":"可见","image":"https://www.heavens-above.com/PassSkyChart2.ashx?passID=363217&size=800&lat=39.9042&lng=116.4074&loc=%e5%8c%97%e4%ba%ac%e5%b8%82&alt=52&tz=ChST&showUnlit=true","scoreData":[3,-0.8,-16.8,12],"exist":242,"score":35,"id":"eb4388c77a046446d51b67195b275ec8"},{"url":"https://www.heavens-above.com/passdetails.aspx?lat=39.9042&lng=116.4074&loc=%e5%8c%97%e4%ba%ac%e5%b8%82&alt=52&tz=ChST&satid=25544&mjd=61163.7584293477&type=A","date":"5月4日","brightness":"-0.5","events":{"rise":{"time":"02:07:37","altitude":"0°","azimuth":"305° (西北)","distance":"2,362","brightness":"-","sunAltitude":"-28.0°"},"exitShadow":{"time":"02:10:46","altitude":"9°","azimuth":"338° (西北偏北)","distance":"1,534","brightness":"-0.5","sunAltitude":"-27.7°"},"reachAltitude10deg":{"time":"02:11:01","altitude":"10°","azimuth":"342° (西北偏北)","distance":"1,498","brightness":"-0.5","sunAltitude":"-27.7°"},"highestPoint":{"time":"02:12:08","altitude":"11°","azimuth":"1° (北)","distance":"1,425","brightness":"-0.4","sunAltitude":"-27.6°"},"dropBelowAltitude10deg":{"time":"02:13:14","altitude":"10°","azimuth":"20° (东北偏北)","distance":"1,499","brightness":"0.0","sunAltitude":"-27.4°"},"set":{"time":"02:16:39","altitude":"0°","azimuth":"57° (东北偏东)","distance":"2,362","brightness":"1.1","sunAltitude":"-27.1°"}},"passType":"可见","image":"https://www.heavens-above.com/PassSkyChart2.ashx?passID=363266&size=800&lat=39.9042&lng=116.4074&loc=%e5%8c%97%e4%ba%ac%e5%b8%82&alt=52&tz=ChST&showUnlit=true","scoreData":[2,-0.4,-27.6,11],"exist":148,"score":35,"id":"bf844c4e228111ff69d807930bf3d3a9"},{"url":"https://www.heavens-above.com/passdetails.aspx?lat=39.9042&lng=116.4074&loc=%e5%8c%97%e4%ba%ac%e5%b8%82&alt=52&tz=ChST&satid=25544&mjd=61161.8254538235&type=A","date":"5月2日","brightness":"-0.7","events":{"rise":{"time":"03:43:57","altitude":"0°","azimuth":"312° (西北)","distance":"2,364","brightness":"-0.1","sunAltitude":"-16.0°"},"reachAltitude10deg":{"time":"03:46:56","altitude":"10°","azimuth":"341° (西北偏北)","distance":"1,499","brightness":"-0.7","sunAltitude":"-15.5°"},"highestPoint":{"time":"03:48:39","altitude":"13°","azimuth":"12° (东北偏北)","distance":"1,314","brightness":"-0.6","sunAltitude":"-15.2°"},"dropBelowAltitude10deg":{"time":"03:50:22","altitude":"10°","azimuth":"42° (东北)","distance":"1,498","brightness":"0.4","sunAltitude":"-15.0°"},"set":{"time":"03:53:21","altitude":"0°","azimuth":"71° (东北偏东)","distance":"2,361","brightness":"1.6","sunAltitude":"-14.5°"}},"passType":"可见","image":"https://www.heavens-above.com/PassSkyChart2.ashx?passID=363175&size=800&lat=39.9042&lng=116.4074&loc=%e5%8c%97%e4%ba%ac%e5%b8%82&alt=52&tz=ChST&showUnlit=true","scoreData":[3,-0.6,-15.2,13],"exist":206,"score":29,"id":"24bc4bd22ff648f2a7b6f5ed96024775"},{"url":"https://www.heavens-above.com/passdetails.aspx?lat=39.9042&lng=116.4074&loc=%e5%8c%97%e4%ba%ac%e5%b8%82&alt=52&tz=ChST&satid=25544&mjd=61147.8183336409&type=A","date":"4月18日","brightness":"-1.0","events":{"rise":{"time":"03:34:02","altitude":"0°","azimuth":"182° (南)","distance":"2,345","brightness":"-","sunAltitude":"-21.4°"},"exitShadow":{"time":"03:37:30","altitude":"10°","azimuth":"143° (东南)","distance":"1,493","brightness":"-1.0","sunAltitude":"-20.9°"},"reachAltitude10deg":{"time":"03:37:32","altitude":"10°","azimuth":"143° (东南)","distance":"1,489","brightness":"-1.0","sunAltitude":"-20.9°"},"highestPoint":{"time":"03:38:24","altitude":"11°","azimuth":"128° (东南)","distance":"1,446","brightness":"-0.8","sunAltitude":"-20.7°"},"dropBelowAltitude10deg":{"time":"03:39:15","altitude":"10°","azimuth":"113° (东南偏东)","distance":"1,493","brightness":"-0.6","sunAltitude":"-20.6°"},"set":{"time":"03:42:47","altitude":"0°","azimuth":"74° (东北偏东)","distance":"2,364","brightness":"1.4","sunAltitude":"-20.0°"}},"passType":"可见","image":"https://www.heavens-above.com/PassSkyChart2.ashx?passID=362903&size=800&lat=39.9042&lng=116.4074&loc=%e5%8c%97%e4%ba%ac%e5%b8%82&alt=52&tz=ChST&showUnlit=true","scoreData":[3,-0.8,-20.7,11],"exist":105,"score":29,"id":"9f204a2e1a25b59e02ab7bb32faa27c0"},{"url":"https://www.heavens-above.com/passdetails.aspx?lat=39.9042&lng=116.4074&loc=%e5%8c%97%e4%ba%ac%e5%b8%82&alt=52&tz=ChST&satid=25544&mjd=61156.8567261425&type=A","date":"4月27日","brightness":"-0.9","events":{"rise":{"time":"04:29:08","altitude":"0°","azimuth":"300° (西北偏西)","distance":"2,363","brightness":"-","sunAltitude":"-9.9°"},"exitShadow":{"time":"04:29:14","altitude":"0°","azimuth":"300° (西北偏西)","distance":"2,327","brightness":"-0.3","sunAltitude":"-9.9°"},"reachAltitude10deg":{"time":"04:32:29","altitude":"10°","azimuth":"336° (西北偏北)","distance":"1,500","brightness":"-0.9","sunAltitude":"-9.3°"},"highestPoint":{"time":"04:33:40","altitude":"11°","azimuth":"356° (北)","distance":"1,415","brightness":"-0.8","sunAltitude":"-9.1°"},"dropBelowAltitude10deg":{"time":"04:34:52","altitude":"10°","azimuth":"17° (东北偏北)","distance":"1,501","brightness":"-0.3","sunAltitude":"-8.9°"},"set":{"time":"04:38:13","altitude":"0°","azimuth":"53° (东北)","distance":"2,366","brightness":"2.1","sunAltitude":"-8.3°"}},"passType":"可见","image":"https://www.heavens-above.com/PassSkyChart2.ashx?passID=363190&size=800&lat=39.9042&lng=116.4074&loc=%e5%8c%97%e4%ba%ac%e5%b8%82&alt=52&tz=ChST&showUnlit=true","scoreData":[4,-0.8,-9.1,11],"exist":338,"score":26,"id":"2149f529c47f39f6764a2f8926416b1c"},{"url":"https://www.heavens-above.com/passdetails.aspx?lat=39.9042&lng=116.4074&loc=%e5%8c%97%e4%ba%ac%e5%b8%82&alt=52&tz=ChST&satid=25544&mjd=61158.8578778485&type=A","date":"4月29日","brightness":"-0.8","events":{"rise":{"time":"04:30:45","altitude":"0°","azimuth":"309° (西北)","distance":"2,364","brightness":"-0.2","sunAltitude":"-9.1°"},"reachAltitude10deg":{"time":"04:33:59","altitude":"10°","azimuth":"343° (西北偏北)","distance":"1,500","brightness":"-0.8","sunAltitude":"-8.5°"},"highestPoint":{"time":"04:35:20","altitude":"12°","azimuth":"7° (北)","distance":"1,390","brightness":"-0.6","sunAltitude":"-8.3°"},"dropBelowAltitude10deg":{"time":"04:36:41","altitude":"10°","azimuth":"30° (东北偏北)","distance":"1,500","brightness":"0.0","sunAltitude":"-8.1°"},"set":{"time":"04:39:55","altitude":"0°","azimuth":"64° (东北偏东)","distance":"2,363","brightness":"2.8","sunAltitude":"-7.5°"}},"passType":"可见","image":"https://www.heavens-above.com/PassSkyChart2.ashx?passID=363169&size=800&lat=39.9042&lng=116.4074&loc=%e5%8c%97%e4%ba%ac%e5%b8%82&alt=52&tz=ChST&showUnlit=true","scoreData":[4,-0.6,-8.3,12],"exist":162,"score":19,"id":"e71445827e8e668fa1fe2262f5ad8465"},{"url":"https://www.heavens-above.com/passdetails.aspx?lat=39.9042&lng=116.4074&loc=%e5%8c%97%e4%ba%ac%e5%b8%82&alt=52&tz=ChST&satid=25544&mjd=61143.8832039285&type=A","date":"4月14日","brightness":"-0.7","events":{"rise":{"time":"05:07:26","altitude":"0°","azimuth":"182° (南)","distance":"2,347","brightness":"-0.2","sunAltitude":"-6.6°"},"reachAltitude10deg":{"time":"05:10:56","altitude":"10°","azimuth":"143° (东南)","distance":"1,492","brightness":"-0.7","sunAltitude":"-6.0°"},"highestPoint":{"time":"05:11:49","altitude":"11°","azimuth":"128° (东南)","distance":"1,447","brightness":"-0.5","sunAltitude":"-5.8°"},"dropBelowAltitude10deg":{"time":"05:12:41","altitude":"10°","azimuth":"113° (东南偏东)","distance":"1,495","brightness":"-0.1","sunAltitude":"-5.7°"},"set":{"time":"05:16:12","altitude":"0°","azimuth":"74° (东北偏东)","distance":"2,366","brightness":"3.2","sunAltitude":"-5.0°"}},"passType":"可见","image":"https://www.heavens-above.com/PassSkyChart2.ashx?passID=362880&size=800&lat=39.9042&lng=116.4074&loc=%e5%8c%97%e4%ba%ac%e5%b8%82&alt=52&tz=ChST&showUnlit=true","scoreData":[5,-0.5,-5.8,11],"exist":105,"score":12,"id":"bac4e4bbecb12c05c2be7561ab37940b"},{"url":"https://www.heavens-above.com/passdetails.aspx?lat=39.9042&lng=116.4074&loc=%e5%8c%97%e4%ba%ac%e5%b8%82&alt=52&tz=ChST&satid=25544&mjd=61156.7891137677&type=A","date":"4月27日","brightness":"-1.6","events":{"rise":{"time":"02:50:48","altitude":"0°","azimuth":"266° (西)","distance":"2,355","brightness":"-","sunAltitude":"-24.9°"},"reachAltitude10deg":{"time":"02:53:11","altitude":"10°","azimuth":"282° (西北偏西)","distance":"1,494","brightness":"-","sunAltitude":"-24.6°"},"highestPoint":{"time":"02:55:55","altitude":"23°","azimuth":"336° (西北偏北)","distance":"952","brightness":"-","sunAltitude":"-24.3°"},"exitShadow":{"time":"02:56:19","altitude":"22°","azimuth":"347° (西北偏北)","distance":"967","brightness":"-1.6","sunAltitude":"-24.2°"},"dropBelowAltitude10deg":{"time":"02:58:40","altitude":"10°","azimuth":"31° (东北偏北)","distance":"1,500","brightness":"0.1","sunAltitude":"-23.9°"},"set":{"time":"03:01:04","altitude":"0°","azimuth":"47° (东北)","distance":"2,366","brightness":"1.5","sunAltitude":"-23.6°"}},"passType":"可见","image":"https://www.heavens-above.com/PassSkyChart2.ashx?passID=363158&size=800&lat=39.9042&lng=116.4074&loc=%e5%8c%97%e4%ba%ac%e5%b8%82&alt=52&tz=ChST&showUnlit=true","scoreData":[2,null,-24.3,23],"exist":141,"score":0,"id":"c0d54d48072723b31479636527fb54c3"},{"url":"https://www.heavens-above.com/passdetails.aspx?lat=39.9042&lng=116.4074&loc=%e5%8c%97%e4%ba%ac%e5%b8%82&alt=52&tz=ChST&satid=25544&mjd=61154.7886695577&type=A","date":"4月25日","brightness":"-2.0","events":{"rise":{"time":"02:49:08","altitude":"0°","azimuth":"245° (西南偏西)","distance":"2,350","brightness":"-","sunAltitude":"-25.8°"},"reachAltitude10deg":{"time":"02:51:16","altitude":"10°","azimuth":"251° (西南偏西)","distance":"1,491","brightness":"-","sunAltitude":"-25.5°"},"highestPoint":{"time":"02:54:31","altitude":"48°","azimuth":"327° (西北偏北)","distance":"557","brightness":"-","sunAltitude":"-25.0°"},"exitShadow":{"time":"02:55:41","altitude":"32°","azimuth":"21° (东北偏北)","distance":"746","brightness":"-2.0","sunAltitude":"-24.9°"},"dropBelowAltitude10deg":{"time":"02:57:47","altitude":"10°","azimuth":"43° (东北)","distance":"1,499","brightness":"0.1","sunAltitude":"-24.6°"},"set":{"time":"02:59:56","altitude":"0°","azimuth":"50° (东北)","distance":"2,366","brightness":"1.5","sunAltitude":"-24.3°"}},"passType":"可见","image":"https://www.heavens-above.com/PassSkyChart2.ashx?passID=363142&size=800&lat=39.9042&lng=116.4074&loc=%e5%8c%97%e4%ba%ac%e5%b8%82&alt=52&tz=ChST&showUnlit=true","scoreData":[2,null,-25,48],"exist":126,"score":0,"id":"ad64e107423c56563532a45362413111"},{"url":"https://www.heavens-above.com/passdetails.aspx?lat=39.9042&lng=116.4074&loc=%e5%8c%97%e4%ba%ac%e5%b8%82&alt=52&tz=ChST&satid=25544&mjd=61152.7880497215&type=A","date":"4月23日","brightness":"-1.7","events":{"rise":{"time":"02:47:51","altitude":"0°","azimuth":"222° (西南)","distance":"2,346","brightness":"-","sunAltitude":"-26.5°"},"reachAltitude10deg":{"time":"02:49:57","altitude":"10°","azimuth":"218° (西南)","distance":"1,488","brightness":"-","sunAltitude":"-26.3°"},"highestPoint":{"time":"02:53:14","altitude":"57°","azimuth":"139° (东南)","distance":"495","brightness":"-","sunAltitude":"-25.8°"},"exitShadow":{"time":"02:54:47","altitude":"27°","azimuth":"70° (东北偏东)","distance":"830","brightness":"-1.7","sunAltitude":"-25.6°"},"dropBelowAltitude10deg":{"time":"02:56:32","altitude":"10°","azimuth":"60° (东北偏东)","distance":"1,498","brightness":"0.0","sunAltitude":"-25.4°"},"set":{"time":"02:58:39","altitude":"0°","azimuth":"56° (东北)","distance":"2,366","brightness":"1.4","sunAltitude":"-25.1°"}},"passType":"可见","image":"https://www.heavens-above.com/PassSkyChart2.ashx?passID=362944&size=800&lat=39.9042&lng=116.4074&loc=%e5%8c%97%e4%ba%ac%e5%b8%82&alt=52&tz=ChST&showUnlit=true","scoreData":[2,null,-25.8,57],"exist":105,"score":0,"id":"406469e22b763d1f5e9deef155e60a51"},{"url":"https://www.heavens-above.com/passdetails.aspx?lat=39.9042&lng=116.4074&loc=%e5%8c%97%e4%ba%ac%e5%b8%82&alt=52&tz=ChST&satid=25544&mjd=61124.5399617691&type=A","date":"3月25日","brightness":"-1.2","events":{"rise":{"time":"20:54:04","altitude":"0°","azimuth":"306° (西北)","distance":"2,378","brightness":"1.3","sunAltitude":"-27.0°"},"reachAltitude10deg":{"time":"20:56:11","altitude":"10°","azimuth":"305° (西北)","distance":"1,509","brightness":"0.0","sunAltitude":"-27.4°"},"enterShadow":{"time":"20:57:32","altitude":"22°","azimuth":"303° (西北偏西)","distance":"968","brightness":"-1.2","sunAltitude":"-27.6°"},"highestPoint":{"time":"20:59:34","altitude":"79°","azimuth":"218° (西南)","distance":"432","brightness":"-","sunAltitude":"-28.0°"},"dropBelowAltitude10deg":{"time":"21:02:55","altitude":"10°","azimuth":"133° (东南)","distance":"1,496","brightness":"-","sunAltitude":"-28.5°"},"set":{"time":"21:05:00","altitude":"0°","azimuth":"132° (东南)","distance":"2,355","brightness":"-","sunAltitude":"-28.9°"}},"passType":"可见","image":"https://www.heavens-above.com/PassSkyChart2.ashx?passID=362551&size=800&lat=39.9042&lng=116.4074&loc=%e5%8c%97%e4%ba%ac%e5%b8%82&alt=52&tz=ChST&showUnlit=true","scoreData":[20,null,-28,79],"exist":81,"score":0,"id":"cb9d50f080e1ad84435121f8adfd201b"},{"url":"https://www.heavens-above.com/passdetails.aspx?lat=39.9042&lng=116.4074&loc=%e5%8c%97%e4%ba%ac%e5%b8%82&alt=52&tz=ChST&satid=25544&mjd=61126.5420707067&type=A","date":"3月27日","brightness":"-1.0","events":{"rise":{"time":"20:56:57","altitude":"0°","azimuth":"297° (西北偏西)","distance":"2,375","brightness":"1.4","sunAltitude":"-27.1°"},"reachAltitude10deg":{"time":"20:59:18","altitude":"10°","azimuth":"283° (西北偏西)","distance":"1,506","brightness":"-0.1","sunAltitude":"-27.4°"},"enterShadow":{"time":"21:00:34","altitude":"18°","azimuth":"266° (西)","distance":"1,121","brightness":"-1.0","sunAltitude":"-27.7°"},"highestPoint":{"time":"21:02:06","altitude":"24°","azimuth":"227° (西南)","distance":"908","brightness":"-","sunAltitude":"-27.9°"},"dropBelowAltitude10deg":{"time":"21:04:53","altitude":"10°","azimuth":"171° (南)","distance":"1,494","brightness":"-","sunAltitude":"-28.4°"},"set":{"time":"21:07:12","altitude":"0°","azimuth":"157° (东南偏南)","distance":"2,352","brightness":"-","sunAltitude":"-28.7°"}},"passType":"可见","image":"https://www.heavens-above.com/PassSkyChart2.ashx?passID=362603&size=800&lat=39.9042&lng=116.4074&loc=%e5%8c%97%e4%ba%ac%e5%b8%82&alt=52&tz=ChST&showUnlit=true","scoreData":[21,null,-27.9,24],"exist":76,"score":0,"id":"cf92eb722d0f00f6079d8d49db1b03d0"},{"url":"https://www.heavens-above.com/passdetails.aspx?lat=39.9042&lng=116.4074&loc=%e5%8c%97%e4%ba%ac%e5%b8%82&alt=52&tz=ChST&satid=25544&mjd=61159.7572543388&type=A","date":"4月30日","brightness":"-0.8","events":{"rise":{"time":"02:04:22","altitude":"0°","azimuth":"275° (西)","distance":"2,356","brightness":"-","sunAltitude":"-29.5°"},"reachAltitude10deg":{"time":"02:06:57","altitude":"10°","azimuth":"296° (西北偏西)","distance":"1,495","brightness":"-","sunAltitude":"-29.2°"},"highestPoint":{"time":"02:09:18","altitude":"18°","azimuth":"341° (西北偏北)","distance":"1,120","brightness":"-","sunAltitude":"-29.0°"},"exitShadow":{"time":"02:10:27","altitude":"15°","azimuth":"6° (北)","distance":"1,219","brightness":"-0.8","sunAltitude":"-28.9°"},"dropBelowAltitude10deg":{"time":"02:11:40","altitude":"10°","azimuth":"26° (东北偏北)","distance":"1,499","brightness":"0.0","sunAltitude":"-28.7°"},"set":{"time":"02:14:16","altitude":"0°","azimuth":"46° (东北)","distance":"2,365","brightness":"1.2","sunAltitude":"-28.5°"}},"passType":"可见","image":"https://www.heavens-above.com/PassSkyChart2.ashx?passID=363182&size=800&lat=39.9042&lng=116.4074&loc=%e5%8c%97%e4%ba%ac%e5%b8%82&alt=52&tz=ChST&showUnlit=true","scoreData":[2,null,-29,18],"exist":73,"score":0,"id":"6487985d5a66becb93aa37aab1f5b813"},{"url":"https://www.heavens-above.com/passdetails.aspx?lat=39.9042&lng=116.4074&loc=%e5%8c%97%e4%ba%ac%e5%b8%82&alt=52&tz=ChST&satid=25544&mjd=61122.5379373681&type=A","date":"3月23日","brightness":"-1.1","events":{"rise":{"time":"20:51:17","altitude":"0°","azimuth":"312° (西北)","distance":"2,379","brightness":"1.3","sunAltitude":"-27.1°"},"reachAltitude10deg":{"time":"20:53:30","altitude":"10°","azimuth":"321° (西北)","distance":"1,511","brightness":"-0.1","sunAltitude":"-27.4°"},"enterShadow":{"time":"20:54:37","altitude":"18°","azimuth":"331° (西北偏北)","distance":"1,105","brightness":"-1.1","sunAltitude":"-27.6°"},"highestPoint":{"time":"20:56:40","altitude":"37°","azimuth":"30° (东北偏北)","distance":"677","brightness":"-","sunAltitude":"-28.0°"},"dropBelowAltitude10deg":{"time":"20:59:50","altitude":"10°","azimuth":"100° (东)","distance":"1,500","brightness":"-","sunAltitude":"-28.5°"},"set":{"time":"21:02:01","altitude":"0°","azimuth":"109° (东南偏东)","distance":"2,360","brightness":"-","sunAltitude":"-28.9°"}},"passType":"可见","image":"https://www.heavens-above.com/PassSkyChart2.ashx?passID=362567&size=800&lat=39.9042&lng=116.4074&loc=%e5%8c%97%e4%ba%ac%e5%b8%82&alt=52&tz=ChST&showUnlit=true","scoreData":[20,null,-28,37],"exist":67,"score":0,"id":"926161a55fef6aaf0ab787ac286d4a03"},{"url":"https://www.heavens-above.com/passdetails.aspx?lat=39.9042&lng=116.4074&loc=%e5%8c%97%e4%ba%ac%e5%b8%82&alt=52&tz=ChST&satid=25544&mjd=61150.7872126794&type=A","date":"4月21日","brightness":"-1.0","events":{"rise":{"time":"02:47:10","altitude":"0°","azimuth":"197° (西南偏南)","distance":"2,344","brightness":"-","sunAltitude":"-27.2°"},"reachAltitude10deg":{"time":"02:49:40","altitude":"10°","azimuth":"178° (南)","distance":"1,487","brightness":"-","sunAltitude":"-26.9°"},"highestPoint":{"time":"02:52:04","altitude":"19°","azimuth":"131° (东南)","distance":"1,074","brightness":"-","sunAltitude":"-26.6°"},"exitShadow":{"time":"02:53:35","altitude":"14°","azimuth":"98° (东)","distance":"1,255","brightness":"-1.0","sunAltitude":"-26.4°"},"dropBelowAltitude10deg":{"time":"02:54:30","altitude":"10°","azimuth":"85° (东)","distance":"1,496","brightness":"-0.4","sunAltitude":"-26.3°"},"set":{"time":"02:57:00","altitude":"0°","azimuth":"66° (东北偏东)","distance":"2,364","brightness":"1.2","sunAltitude":"-25.9°"}},"passType":"可见","image":"https://www.heavens-above.com/PassSkyChart2.ashx?passID=362941&size=800&lat=39.9042&lng=116.4074&loc=%e5%8c%97%e4%ba%ac%e5%b8%82&alt=52&tz=ChST&showUnlit=true","scoreData":[2,null,-26.6,19],"exist":55,"score":0,"id":"d0c07a9434aa250d4c532d1b54332b85"},{"url":"https://www.heavens-above.com/passdetails.aspx?lat=39.9042&lng=116.4074&loc=%e5%8c%97%e4%ba%ac%e5%b8%82&alt=52&tz=ChST&satid=25544&mjd=61157.757013979&type=A","date":"4月28日","brightness":"-0.7","events":{"rise":{"time":"02:02:40","altitude":"0°","azimuth":"255° (西南偏西)","distance":"2,352","brightness":"-","sunAltitude":"-30.3°"},"reachAltitude10deg":{"time":"02:04:54","altitude":"10°","azimuth":"266° (西)","distance":"1,492","brightness":"-","sunAltitude":"-30.0°"},"highestPoint":{"time":"02:07:57","altitude":"31°","azimuth":"331° (西北偏北)","distance":"751","brightness":"-","sunAltitude":"-29.7°"},"exitShadow":{"time":"02:10:06","altitude":"16°","azimuth":"28° (东北偏北)","distance":"1,182","brightness":"-0.7","sunAltitude":"-29.5°"},"dropBelowAltitude10deg":{"time":"02:11:00","altitude":"10°","azimuth":"37° (东北)","distance":"1,499","brightness":"0.0","sunAltitude":"-29.4°"},"set":{"time":"02:13:15","altitude":"0°","azimuth":"48° (东北)","distance":"2,365","brightness":"1.2","sunAltitude":"-29.2°"}},"passType":"可见","image":"https://www.heavens-above.com/PassSkyChart2.ashx?passID=363177&size=800&lat=39.9042&lng=116.4074&loc=%e5%8c%97%e4%ba%ac%e5%b8%82&alt=52&tz=ChST&showUnlit=true","scoreData":[2,null,-29.7,31],"exist":54,"score":0,"id":"46caeeeba06cd90adea6ff5676702dd2"},{"url":"https://www.heavens-above.com/passdetails.aspx?lat=39.9042&lng=116.4074&loc=%e5%8c%97%e4%ba%ac%e5%b8%82&alt=52&tz=ChST&satid=25544&mjd=61120.5359261134&type=A","date":"3月21日","brightness":"-0.8","events":{"rise":{"time":"20:48:23","altitude":"0°","azimuth":"313° (西北)","distance":"2,380","brightness":"1.2","sunAltitude":"-27.0°"},"reachAltitude10deg":{"time":"20:50:56","altitude":"10°","azimuth":"332° (西北偏北)","distance":"1,512","brightness":"-0.3","sunAltitude":"-27.5°"},"enterShadow":{"time":"20:51:43","altitude":"14°","azimuth":"343° (西北偏北)","distance":"1,298","brightness":"-0.8","sunAltitude":"-27.6°"},"highestPoint":{"time":"20:53:27","altitude":"19°","azimuth":"20° (东北偏北)","distance":"1,074","brightness":"-","sunAltitude":"-27.9°"},"dropBelowAltitude10deg":{"time":"20:55:58","altitude":"10°","azimuth":"69° (东北偏东)","distance":"1,505","brightness":"-","sunAltitude":"-28.3°"},"set":{"time":"20:58:29","altitude":"0°","azimuth":"88° (东)","distance":"2,366","brightness":"-","sunAltitude":"-28.8°"}},"passType":"可见","image":"https://www.heavens-above.com/PassSkyChart2.ashx?passID=362543&size=800&lat=39.9042&lng=116.4074&loc=%e5%8c%97%e4%ba%ac%e5%b8%82&alt=52&tz=ChST&showUnlit=true","scoreData":[20,null,-27.9,19],"exist":47,"score":0,"id":"571cd75f329f29322acb866f62d47609"},{"url":"https://www.heavens-above.com/passdetails.aspx?lat=39.9042&lng=116.4074&loc=%e5%8c%97%e4%ba%ac%e5%b8%82&alt=52&tz=ChST&satid=25544&mjd=61164.7252702317&type=A","date":"5月5日","brightness":"-0.3","events":{"rise":{"time":"01:19:17","altitude":"0°","azimuth":"299° (西北偏西)","distance":"2,360","brightness":"-","sunAltitude":"-31.8°"},"reachAltitude10deg":{"time":"01:22:37","altitude":"10°","azimuth":"335° (西北偏北)","distance":"1,498","brightness":"-","sunAltitude":"-31.6°"},"highestPoint":{"time":"01:23:49","altitude":"12°","azimuth":"356° (北)","distance":"1,411","brightness":"-","sunAltitude":"-31.5°"},"exitShadow":{"time":"01:24:23","altitude":"11°","azimuth":"6° (北)","distance":"1,431","brightness":"-0.3","sunAltitude":"-31.4°"},"dropBelowAltitude10deg":{"time":"01:25:02","altitude":"10°","azimuth":"17° (东北偏北)","distance":"1,498","brightness":"-0.1","sunAltitude":"-31.4°"},"set":{"time":"01:28:22","altitude":"0°","azimuth":"53° (东北)","distance":"2,363","brightness":"0.9","sunAltitude":"-31.2°"}},"passType":"可见","image":"https://www.heavens-above.com/PassSkyChart2.ashx?passID=363282&size=800&lat=39.9042&lng=116.4074&loc=%e5%8c%97%e4%ba%ac%e5%b8%82&alt=52&tz=ChST&showUnlit=true","scoreData":[1,null,-31.5,12],"exist":39,"score":0,"id":"bc9ed0c9c2a7aeec525ae78f9b16f3cf"},{"url":"https://www.heavens-above.com/passdetails.aspx?lat=39.9042&lng=116.4074&loc=%e5%8c%97%e4%ba%ac%e5%b8%82&alt=52&tz=ChST&satid=25544&mjd=61155.7566467857&type=A","date":"4月26日","brightness":"-0.5","events":{"rise":{"time":"02:01:16","altitude":"0°","azimuth":"234° (西南)","distance":"2,348","brightness":"-","sunAltitude":"-31.0°"},"reachAltitude10deg":{"time":"02:03:21","altitude":"10°","azimuth":"235° (西南)","distance":"1,488","brightness":"-","sunAltitude":"-30.8°"},"highestPoint":{"time":"02:06:42","altitude":"81°","azimuth":"323° (西北)","distance":"426","brightness":"-","sunAltitude":"-30.5°"},"exitShadow":{"time":"02:09:34","altitude":"14°","azimuth":"51° (东北)","distance":"1,294","brightness":"-0.5","sunAltitude":"-30.2°"},"dropBelowAltitude10deg":{"time":"02:10:04","altitude":"10°","azimuth":"51° (东北)","distance":"1,498","brightness":"-0.1","sunAltitude":"-30.1°"},"set":{"time":"02:12:10","altitude":"0°","azimuth":"52° (东北)","distance":"2,365","brightness":"1.1","sunAltitude":"-29.9°"}},"passType":"可见","image":"https://www.heavens-above.com/PassSkyChart2.ashx?passID=363102&size=800&lat=39.9042&lng=116.4074&loc=%e5%8c%97%e4%ba%ac%e5%b8%82&alt=52&tz=ChST&showUnlit=true","scoreData":[2,null,-30.5,81],"exist":30,"score":0,"id":"eee71121bc368a58f0dd02a6a212026b"},{"url":"https://www.heavens-above.com/passdetails.aspx?lat=39.9042&lng=116.4074&loc=%e5%8c%97%e4%ba%ac%e5%b8%82&alt=52&tz=ChST&satid=25544&mjd=61118.5338595328&type=A","date":"3月19日","brightness":"-0.7","events":{"rise":{"time":"20:45:13","altitude":"0°","azimuth":"311° (西北)","distance":"2,381","brightness":"1.2","sunAltitude":"-26.9°"},"reachAltitude10deg":{"time":"20:48:16","altitude":"10°","azimuth":"341° (西北偏北)","distance":"1,513","brightness":"-0.4","sunAltitude":"-27.5°"},"enterShadow":{"time":"20:48:45","altitude":"11°","azimuth":"348° (西北偏北)","distance":"1,430","brightness":"-0.7","sunAltitude":"-27.6°"},"highestPoint":{"time":"20:49:56","altitude":"13°","azimuth":"10° (北)","distance":"1,340","brightness":"-","sunAltitude":"-27.8°"},"dropBelowAltitude10deg":{"time":"20:51:36","altitude":"10°","azimuth":"40° (东北)","distance":"1,509","brightness":"-","sunAltitude":"-28.1°"},"set":{"time":"20:54:37","altitude":"0°","azimuth":"69° (东北偏东)","distance":"2,370","brightness":"-","sunAltitude":"-28.6°"}},"passType":"可见","image":"https://www.heavens-above.com/PassSkyChart2.ashx?passID=362536&size=800&lat=39.9042&lng=116.4074&loc=%e5%8c%97%e4%ba%ac%e5%b8%82&alt=52&tz=ChST&showUnlit=true","scoreData":[20,null,-27.8,13],"exist":29,"score":0,"id":"591502d543ca6a4e8e07970ecde46e82"},{"url":"https://www.heavens-above.com/passdetails.aspx?lat=39.9042&lng=116.4074&loc=%e5%8c%97%e4%ba%ac%e5%b8%82&alt=52&tz=ChST&satid=25544&mjd=61162.7251865741&type=A","date":"5月3日","brightness":"-0.2","events":{"rise":{"time":"01:17:44","altitude":"0°","azimuth":"284° (西北偏西)","distance":"2,358","brightness":"-","sunAltitude":"-32.4°"},"reachAltitude10deg":{"time":"01:20:33","altitude":"10°","azimuth":"310° (西北)","distance":"1,496","brightness":"-","sunAltitude":"-32.3°"},"highestPoint":{"time":"01:22:30","altitude":"15°","azimuth":"346° (西北偏北)","distance":"1,254","brightness":"-","sunAltitude":"-32.1°"},"exitShadow":{"time":"01:24:16","altitude":"11°","azimuth":"18° (东北偏北)","distance":"1,456","brightness":"-0.2","sunAltitude":"-32.0°"},"dropBelowAltitude10deg":{"time":"01:24:24","altitude":"10°","azimuth":"20° (东北偏北)","distance":"1,486","brightness":"-0.1","sunAltitude":"-32.0°"},"set":{"time":"01:27:17","altitude":"0°","azimuth":"47° (东北)","distance":"2,364","brightness":"0.9","sunAltitude":"-31.8°"}},"passType":"可见","image":"https://www.heavens-above.com/PassSkyChart2.ashx?passID=363201&size=800&lat=39.9042&lng=116.4074&loc=%e5%8c%97%e4%ba%ac%e5%b8%82&alt=52&tz=ChST&showUnlit=true","scoreData":[1,null,-32.1,15],"exist":8,"score":0,"id":"bea6e16243c229d5e843c396f2dda189"}]